design.v
// ============================================================================
// RAM Module - Parameterized Synchronous Memory
// ============================================================================
module RAM #(
    parameter ADDR_WIDTH = 16,
    parameter DATA_WIDTH = 32,
    parameter MEM_SIZE = 65536  // 2^16
)(
    input wire clk,
    input wire read_enable,
    input wire write_enable,
    input wire [ADDR_WIDTH-1:0] address,
    input wire [DATA_WIDTH-1:0] write_data,
    output reg [DATA_WIDTH-1:0] read_data,
    output reg ready
);

    // Memory array
    reg [DATA_WIDTH-1:0] memory [0:MEM_SIZE-1];
    
    // Initialize memory with some test data
    integer i;
    initial begin
        for (i = 0; i < MEM_SIZE; i = i + 1) begin
            memory[i] = i * 10;  // Test pattern
        end
    end
    
    // Synchronous read/write operations
    always @(posedge clk) begin
        ready <= 0;
        
        if (write_enable) begin
            memory[address] <= write_data;
            ready <= 1;
        end
        else if (read_enable) begin
            read_data <= memory[address];
            ready <= 1;
        end
    end

endmodule

// ============================================================================
// Cache Controller with Integrated Cache - Simplified Version
// ============================================================================
module CacheController #(
    parameter ADDR_WIDTH = 16,
    parameter DATA_WIDTH = 32,
    parameter NUM_SETS = 64,
    parameter NUM_WAYS = 4,
    parameter TAG_WIDTH = 8,
    parameter SET_INDEX_WIDTH = 6,
    parameter OFFSET_WIDTH = 2
)(
    input wire clk,
    input wire rst,
    
    // CPU interface
    input wire [ADDR_WIDTH-1:0] cpu_address,
    input wire [DATA_WIDTH-1:0] cpu_write_data,
    input wire cpu_read_enable,
    input wire cpu_write_enable,
    output reg [DATA_WIDTH-1:0] cpu_read_data,
    output reg cpu_ready,
    
    // RAM interface
    output reg [ADDR_WIDTH-1:0] ram_address,
    output reg [DATA_WIDTH-1:0] ram_write_data,
    output reg ram_read_enable,
    output reg ram_write_enable,
    input wire [DATA_WIDTH-1:0] ram_read_data,
    input wire ram_ready
);

    // Cache storage
    reg [DATA_WIDTH-1:0] cache_data [0:NUM_SETS-1][0:NUM_WAYS-1];
    reg [TAG_WIDTH-1:0] cache_tags [0:NUM_SETS-1][0:NUM_WAYS-1];
    reg cache_valid [0:NUM_SETS-1][0:NUM_WAYS-1];
    reg [1:0] lru_counter [0:NUM_SETS-1][0:NUM_WAYS-1];
    
    // Address decode registers
    reg [TAG_WIDTH-1:0] tag;
    reg [SET_INDEX_WIDTH-1:0] set_index;
    reg is_read_op;
    reg is_write_op;
    
    // Cache control
    reg cache_hit;
    reg [1:0] hit_way_idx;
    reg [1:0] replace_way_idx;
    
    integer i, j;
    
    // Initialize cache and LRU
    initial begin
        for (i = 0; i < NUM_SETS; i = i + 1) begin
            for (j = 0; j < NUM_WAYS; j = j + 1) begin
                cache_data[i][j] = 0;
                cache_tags[i][j] = 0;
                cache_valid[i][j] = 0;
                lru_counter[i][j] = j[1:0];
            end
        end
    end
    
    // FSM states
    localparam IDLE = 3'd0;
    localparam DECODE = 3'd1;
    localparam CHECK_CACHE = 3'd2;
    localparam RAM_READ = 3'd3;
    localparam UPDATE_CACHE = 3'd4;
    localparam RAM_WRITE = 3'd5;
    localparam COMPLETE = 3'd6;
    
    reg [2:0] state;
    reg waiting_for_ram;
    
    // State machine and cache logic
    always @(posedge clk) begin
        if (rst) begin
            state <= IDLE;
            cpu_ready <= 0;
            ram_read_enable <= 0;
            ram_write_enable <= 0;
            waiting_for_ram <= 0;
            
            // Clear valid bits
            for (i = 0; i < NUM_SETS; i = i + 1) begin
                for (j = 0; j < NUM_WAYS; j = j + 1) begin
                    cache_valid[i][j] <= 0;
                    lru_counter[i][j] <= j[1:0];
                end
            end
        end
        else begin
            // Default outputs
            cpu_ready <= 0;
            ram_read_enable <= 0;
            ram_write_enable <= 0;
            
            case (state)
                IDLE: begin
                    if (cpu_read_enable || cpu_write_enable) begin
                        // Decode address and capture operation type
                        tag <= cpu_address[ADDR_WIDTH-1:ADDR_WIDTH-TAG_WIDTH];
                        set_index <= cpu_address[ADDR_WIDTH-TAG_WIDTH-1:OFFSET_WIDTH];
                        ram_address <= cpu_address;
                        ram_write_data <= cpu_write_data;
                        is_read_op <= cpu_read_enable;
                        is_write_op <= cpu_write_enable;
                        state <= DECODE;
                    end
                end
                
                DECODE: begin
                    state <= CHECK_CACHE;
                end
                
                CHECK_CACHE: begin
                    // Check all ways for hit
                    cache_hit = 0;
                    hit_way_idx = 0;
                    
                    for (i = 0; i < NUM_WAYS; i = i + 1) begin
                        if (cache_valid[set_index][i] && cache_tags[set_index][i] == tag) begin
                            cache_hit = 1;
                            hit_way_idx = i[1:0];
                        end
                    end
                    
                    // Find replacement way (do this regardless of hit/miss)
                    replace_way_idx = 0;
                    
                    // First check for invalid way
                    for (i = 0; i < NUM_WAYS; i = i + 1) begin
                        if (!cache_valid[set_index][i]) begin
                            replace_way_idx = i[1:0];
                        end
                    end
                    
                    // If all valid, find LRU
                    if (cache_valid[set_index][0] && cache_valid[set_index][1] && 
                        cache_valid[set_index][2] && cache_valid[set_index][3]) begin
                        for (i = 0; i < NUM_WAYS; i = i + 1) begin
                            if (lru_counter[set_index][i] == 0) begin
                                replace_way_idx = i[1:0];
                            end
                        end
                    end
                    
                    if (cache_hit) begin
                        // Cache hit
                        cpu_read_data <= cache_data[set_index][hit_way_idx];
                        
                        // Update LRU
                        lru_counter[set_index][hit_way_idx] <= 3;
                        for (i = 0; i < NUM_WAYS; i = i + 1) begin
                            if (i != hit_way_idx && lru_counter[set_index][i] > 0) begin
                                lru_counter[set_index][i] <= lru_counter[set_index][i] - 1;
                            end
                        end
                        
                        if (is_write_op) begin
                            // Write hit - update cache and write through to RAM
                            cache_data[set_index][hit_way_idx] <= cpu_write_data;
                            ram_write_enable <= 1;
                            waiting_for_ram <= 1;
                            state <= RAM_WRITE;
                        end
                        else begin
                            // Read hit - done
                            state <= COMPLETE;
                        end
                    end
                    else begin
                        // Cache miss
                        if (is_read_op) begin
                            // Read miss - fetch from RAM
                            ram_read_enable <= 1;
                            waiting_for_ram <= 1;
                            state <= RAM_READ;
                        end
                        else begin
                            // Write miss - write to RAM only (no cache allocation on write miss)
                            ram_write_enable <= 1;
                            waiting_for_ram <= 1;
                            state <= RAM_WRITE;
                        end
                    end
                end
                
                RAM_READ: begin
                    if (waiting_for_ram) begin
                        ram_read_enable <= 1;
                        if (ram_ready) begin
                            waiting_for_ram <= 0;
                            state <= UPDATE_CACHE;
                        end
                    end
                end
                
                UPDATE_CACHE: begin
                    // Update cache with data from RAM
                    cache_data[set_index][replace_way_idx] <= ram_read_data;
                    cache_tags[set_index][replace_way_idx] <= tag;
                    cache_valid[set_index][replace_way_idx] <= 1;
                    cpu_read_data <= ram_read_data;
                    
                    // Update LRU
                    lru_counter[set_index][replace_way_idx] <= 3;
                    for (i = 0; i < NUM_WAYS; i = i + 1) begin
                        if (i != replace_way_idx && lru_counter[set_index][i] > 0) begin
                            lru_counter[set_index][i] <= lru_counter[set_index][i] - 1;
                        end
                    end
                    
                    state <= COMPLETE;
                end
                
                RAM_WRITE: begin
                    if (waiting_for_ram) begin
                        ram_write_enable <= 1;
                        if (ram_ready) begin
                            waiting_for_ram <= 0;
                            state <= COMPLETE;
                        end
                    end
                end
                
                COMPLETE: begin
                    cpu_ready <= 1;
                    state <= IDLE;
                end
                
                default: state <= IDLE;
            endcase
        end
    end

endmodule

// ============================================================================
// Top-Level Module - Complete Cache System
// ============================================================================
module CacheSystem #(
    parameter ADDR_WIDTH = 16,
    parameter DATA_WIDTH = 32,
    parameter NUM_SETS = 64,
    parameter NUM_WAYS = 4
)(
    input wire clk,
    input wire rst,
    
    // CPU interface
    input wire [ADDR_WIDTH-1:0] cpu_address,
    input wire [DATA_WIDTH-1:0] cpu_write_data,
    input wire cpu_read_enable,
    input wire cpu_write_enable,
    output wire [DATA_WIDTH-1:0] cpu_read_data,
    output wire cpu_ready
);

    // Internal signals
    wire [ADDR_WIDTH-1:0] ram_address;
    wire [DATA_WIDTH-1:0] ram_write_data;
    wire ram_read_enable;
    wire ram_write_enable;
    wire [DATA_WIDTH-1:0] ram_read_data;
    wire ram_ready;
    
    // Instantiate RAM
    RAM #(
        .ADDR_WIDTH(ADDR_WIDTH),
        .DATA_WIDTH(DATA_WIDTH)
    ) ram_inst (
        .clk(clk),
        .read_enable(ram_read_enable),
        .write_enable(ram_write_enable),
        .address(ram_address),
        .write_data(ram_write_data),
        .read_data(ram_read_data),
        .ready(ram_ready)
    );
    
    // Instantiate Cache Controller
    CacheController #(
        .ADDR_WIDTH(ADDR_WIDTH),
        .DATA_WIDTH(DATA_WIDTH),
        .NUM_SETS(NUM_SETS),
        .NUM_WAYS(NUM_WAYS)
    ) controller_inst (
        .clk(clk),
        .rst(rst),
        .cpu_address(cpu_address),
        .cpu_write_data(cpu_write_data),
        .cpu_read_enable(cpu_read_enable),
        .cpu_write_enable(cpu_write_enable),
        .cpu_read_data(cpu_read_data),
        .cpu_ready(cpu_ready),
        .ram_address(ram_address),
        .ram_write_data(ram_write_data),
        .ram_read_enable(ram_read_enable),
        .ram_write_enable(ram_write_enable),
        .ram_read_data(ram_read_data),
        .ram_ready(ram_ready)
    );

endmodule

tb_cache_system.v
`timescale 1ns/1ps

module tb_cache_system;

    // Parameters
    parameter ADDR_WIDTH = 16;
    parameter DATA_WIDTH = 32;
    parameter NUM_SETS = 64;
    parameter NUM_WAYS = 4;
    parameter CLK_PERIOD = 10;
    
    // Signals
    reg clk;
    reg rst;
    reg [ADDR_WIDTH-1:0] cpu_address;
    reg [DATA_WIDTH-1:0] cpu_write_data;
    reg cpu_read_enable;
    reg cpu_write_enable;
    wire [DATA_WIDTH-1:0] cpu_read_data;
    wire cpu_ready;
    
    // Statistics
    integer total_reads = 0;
    integer total_writes = 0;
    integer cache_hits = 0;
    integer cache_misses = 0;
    
    // Instantiate the cache system
    CacheSystem #(
        .ADDR_WIDTH(ADDR_WIDTH),
        .DATA_WIDTH(DATA_WIDTH),
        .NUM_SETS(NUM_SETS),
        .NUM_WAYS(NUM_WAYS)
    ) dut (
        .clk(clk),
        .rst(rst),
        .cpu_address(cpu_address),
        .cpu_write_data(cpu_write_data),
        .cpu_read_enable(cpu_read_enable),
        .cpu_write_enable(cpu_write_enable),
        .cpu_read_data(cpu_read_data),
        .cpu_ready(cpu_ready)
    );
    
    // Clock generation
    initial begin
        clk = 0;
        forever #(CLK_PERIOD/2) clk = ~clk;
    end
    
    // Task to perform read operation
    task read_memory(input [ADDR_WIDTH-1:0] addr);
        begin
            @(posedge clk);
            cpu_address = addr;
            cpu_read_enable = 1;
            cpu_write_enable = 0;
            total_reads = total_reads + 1;
            
            @(posedge clk);
            cpu_read_enable = 0;
            
            // Wait for operation to complete
            wait(cpu_ready);
            @(posedge clk);
            
            $display("Time=%0t | READ  | Addr=0x%04h | Data=0x%08h", 
                     $time, addr, cpu_read_data);
        end
    endtask
    
    // Task to perform write operation
    task write_memory(input [ADDR_WIDTH-1:0] addr, input [DATA_WIDTH-1:0] data);
        begin
            @(posedge clk);
            cpu_address = addr;
            cpu_write_data = data;
            cpu_read_enable = 0;
            cpu_write_enable = 1;
            total_writes = total_writes + 1;
            
            @(posedge clk);
            cpu_write_enable = 0;
            
            // Wait for operation to complete
            wait(cpu_ready);
            @(posedge clk);
            
            $display("Time=%0t | WRITE | Addr=0x%04h | Data=0x%08h", 
                     $time, addr, data);
        end
    endtask
    
    // Test stimulus
    initial begin
        // Initialize waveform dump
        $dumpfile("cache_system.vcd");
        $dumpvars(0, tb_cache_system);
        
        // Initialize signals
        rst = 1;
        cpu_address = 0;
        cpu_write_data = 0;
        cpu_read_enable = 0;
        cpu_write_enable = 0;
        
        // Reset
        repeat(5) @(posedge clk);
        rst = 0;
        repeat(2) @(posedge clk);
        
        $display("\n========================================");
        $display("Starting Cache System Test");
        $display("========================================\n");
        
        // Test 1: Simple read (cache miss - first access)
        $display("--- Test 1: Initial Reads (Cache Misses) ---");
        read_memory(16'h0000);
        read_memory(16'h0004);
        read_memory(16'h0008);
        read_memory(16'h000C);
        
        // Test 2: Read same addresses (cache hits)
        $display("\n--- Test 2: Repeated Reads (Cache Hits) ---");
        read_memory(16'h0000);
        read_memory(16'h0004);
        read_memory(16'h0008);
        
        // Test 3: Write operations
        $display("\n--- Test 3: Write Operations ---");
        write_memory(16'h0100, 32'hDEADBEEF);
        write_memory(16'h0104, 32'hCAFEBABE);
        write_memory(16'h0108, 32'h12345678);
        
        // Test 4: Read back written data (should be cache hits)
        $display("\n--- Test 4: Read Back Written Data ---");
        read_memory(16'h0100);
        read_memory(16'h0104);
        read_memory(16'h0108);
        
        // Test 5: Test same set, different tags (to test associativity)
        $display("\n--- Test 5: Testing 4-Way Associativity ---");
        // These addresses map to the same set but different tags
        read_memory(16'h0010);  // Set 4, Tag 0
        read_memory(16'h0410);  // Set 4, Tag 1
        read_memory(16'h0810);  // Set 4, Tag 2
        read_memory(16'h0C10);  // Set 4, Tag 3
        
        // Test 6: Read them again (all should be cache hits)
        $display("\n--- Test 6: Read Same Set (Cache Hits) ---");
        read_memory(16'h0010);
        read_memory(16'h0410);
        read_memory(16'h0810);
        read_memory(16'h0C10);
        
        // Test 7: Force a replacement (5th way in same set)
        $display("\n--- Test 7: Testing LRU Replacement ---");
        read_memory(16'h1010);  // Set 4, Tag 4 - should replace LRU
        
        // Test 8: Sequential access pattern
        $display("\n--- Test 8: Sequential Access Pattern ---");
        read_memory(16'h0200);
        read_memory(16'h0204);
        read_memory(16'h0208);
        read_memory(16'h020C);
        read_memory(16'h0210);
        
        // Test 9: Write and read back immediately
        $display("\n--- Test 9: Write-Through Verification ---");
        write_memory(16'h0300, 32'hA5A5A5A5);
        read_memory(16'h0300);
        
        // Test 10: Random access pattern
        $display("\n--- Test 10: Random Access Pattern ---");
        read_memory(16'h1234);
        read_memory(16'h5678);
        read_memory(16'h9ABC);
        read_memory(16'hDEF0);
        
        // Test 11: Burst write
        $display("\n--- Test 11: Burst Write Operations ---");
        write_memory(16'h0500, 32'h11111111);
        write_memory(16'h0504, 32'h22222222);
        write_memory(16'h0508, 32'h33333333);
        write_memory(16'h050C, 32'h44444444);
        
        // Test 12: Burst read
        $display("\n--- Test 12: Burst Read Operations ---");
        read_memory(16'h0500);
        read_memory(16'h0504);
        read_memory(16'h0508);
        read_memory(16'h050C);
        
        // Test 13: Test conflict scenario
        $display("\n--- Test 13: Cache Conflict Scenario ---");
        // Fill up all ways in a set
        write_memory(16'h0020, 32'hAAAAAAAA);
        write_memory(16'h0420, 32'hBBBBBBBB);
        write_memory(16'h0820, 32'hCCCCCCCC);
        write_memory(16'h0C20, 32'hDDDDDDDD);
        
        // Access them to establish LRU order
        read_memory(16'h0020);
        read_memory(16'h0420);
        read_memory(16'h0820);
        read_memory(16'h0C20);
        
        // Add 5th element - should evict 0x0020 (LRU)
        write_memory(16'h1020, 32'hEEEEEEEE);
        read_memory(16'h1020);
        
        // Try to read evicted address (should be miss and reload)
        read_memory(16'h0020);
        
        // Wait some time
        repeat(10) @(posedge clk);
        
        // Print statistics
        $display("\n========================================");
        $display("Test Complete - Statistics");
        $display("========================================");
        $display("Total Reads:  %0d", total_reads);
        $display("Total Writes: %0d", total_writes);
        $display("Total Operations: %0d", total_reads + total_writes);
        $display("========================================\n");
        
        // Finish simulation
        $display("Simulation completed successfully!");
        #100;
        $finish;
    end
    
    // Monitor for debugging
    initial begin
        $monitor("Time=%0t | State=%0d | Addr=0x%04h | Ready=%b | Hit=%b", 
                 $time, dut.controller_inst.state, cpu_address, cpu_ready,
                 dut.controller_inst.cache_hit);
    end
    
    // Timeout watchdog
    initial begin
        #100000;
        $display("ERROR: Simulation timeout!");
        $finish;
    end

endmodule

cache_system.vcd
$date
	Wed Dec 24 00:18:20 2025
$end
$version
	Icarus Verilog
$end
$timescale
	1ps
$end
$scope module tb_cache_system $end
$var wire 1 ! cpu_ready $end
$var wire 32 " cpu_read_data [31:0] $end
$var parameter 32 # ADDR_WIDTH $end
$var parameter 32 $ CLK_PERIOD $end
$var parameter 32 % DATA_WIDTH $end
$var parameter 32 & NUM_SETS $end
$var parameter 32 ' NUM_WAYS $end
$var reg 1 ( clk $end
$var reg 16 ) cpu_address [15:0] $end
$var reg 1 * cpu_read_enable $end
$var reg 32 + cpu_write_data [31:0] $end
$var reg 1 , cpu_write_enable $end
$var reg 1 - rst $end
$var integer 32 . cache_hits [31:0] $end
$var integer 32 / cache_misses [31:0] $end
$var integer 32 0 total_reads [31:0] $end
$var integer 32 1 total_writes [31:0] $end
$scope module dut $end
$var wire 1 ( clk $end
$var wire 16 2 cpu_address [15:0] $end
$var wire 1 * cpu_read_enable $end
$var wire 32 3 cpu_write_data [31:0] $end
$var wire 1 , cpu_write_enable $end
$var wire 1 - rst $end
$var wire 1 4 ram_write_enable $end
$var wire 32 5 ram_write_data [31:0] $end
$var wire 1 6 ram_ready $end
$var wire 1 7 ram_read_enable $end
$var wire 32 8 ram_read_data [31:0] $end
$var wire 16 9 ram_address [15:0] $end
$var wire 1 ! cpu_ready $end
$var wire 32 : cpu_read_data [31:0] $end
$var parameter 32 ; ADDR_WIDTH $end
$var parameter 32 < DATA_WIDTH $end
$var parameter 32 = NUM_SETS $end
$var parameter 32 > NUM_WAYS $end
$scope module controller_inst $end
$var wire 1 ( clk $end
$var wire 16 ? cpu_address [15:0] $end
$var wire 1 * cpu_read_enable $end
$var wire 32 @ cpu_write_data [31:0] $end
$var wire 1 , cpu_write_enable $end
$var wire 1 - rst $end
$var wire 1 6 ram_ready $end
$var wire 32 A ram_read_data [31:0] $end
$var parameter 32 B ADDR_WIDTH $end
$var parameter 3 C CHECK_CACHE $end
$var parameter 3 D COMPLETE $end
$var parameter 32 E DATA_WIDTH $end
$var parameter 3 F DECODE $end
$var parameter 3 G IDLE $end
$var parameter 32 H NUM_SETS $end
$var parameter 32 I NUM_WAYS $end
$var parameter 32 J OFFSET_WIDTH $end
$var parameter 3 K RAM_READ $end
$var parameter 3 L RAM_WRITE $end
$var parameter 32 M SET_INDEX_WIDTH $end
$var parameter 32 N TAG_WIDTH $end
$var parameter 3 O UPDATE_CACHE $end
$var reg 1 P cache_hit $end
$var reg 32 Q cpu_read_data [31:0] $end
$var reg 1 ! cpu_ready $end
$var reg 2 R hit_way_idx [1:0] $end
$var reg 1 S is_read_op $end
$var reg 1 T is_write_op $end
$var reg 16 U ram_address [15:0] $end
$var reg 1 7 ram_read_enable $end
$var reg 32 V ram_write_data [31:0] $end
$var reg 1 4 ram_write_enable $end
$var reg 2 W replace_way_idx [1:0] $end
$var reg 6 X set_index [5:0] $end
$var reg 3 Y state [2:0] $end
$var reg 8 Z tag [7:0] $end
$var reg 1 [ waiting_for_ram $end
$var integer 32 \ i [31:0] $end
$var integer 32 ] j [31:0] $end
$upscope $end
$scope module ram_inst $end
$var wire 16 ^ address [15:0] $end
$var wire 1 ( clk $end
$var wire 1 7 read_enable $end
$var wire 32 _ write_data [31:0] $end
$var wire 1 4 write_enable $end
$var parameter 32 ` ADDR_WIDTH $end
$var parameter 32 a DATA_WIDTH $end
$var parameter 32 b MEM_SIZE $end
$var reg 32 c read_data [31:0] $end
$var reg 1 6 ready $end
$var integer 32 d i [31:0] $end
$upscope $end
$upscope $end
$scope task read_memory $end
$var reg 16 e addr [15:0] $end
$upscope $end
$scope task write_memory $end
$var reg 16 f addr [15:0] $end
$var reg 32 g data [31:0] $end
$upscope $end
$upscope $end
$enddefinitions $end
$comment Show the parameter values. $end
$dumpall
b10000000000000000 b
b100000 a
b10000 `
b100 O
b1000 N
b110 M
b101 L
b11 K
b10 J
b100 I
b1000000 H
b0 G
b1 F
b100000 E
b110 D
b10 C
b10000 B
b100 >
b1000000 =
b100000 <
b10000 ;
b100 '
b1000000 &
b100000 %
b1010 $
b10000 #
$end
#0
$dumpvars
bx g
bx f
bx e
b10000000000000000 d
bx c
bx _
bx ^
b100 ]
b1000000 \
x[
bx Z
bx Y
bx X
bx W
bx V
bx U
xT
xS
bx R
bx Q
xP
bx A
b0 @
b0 ?
bx :
bx 9
bx 8
x7
x6
bx 5
x4
b0 3
b0 2
b0 1
b0 0
b0 /
b0 .
1-
0,
b0 +
0*
b0 )
0(
bx "
x!
$end
#5000
06
0[
04
07
0!
b0 Y
b100 ]
b1000000 \
1(
#10000
0(
#15000
b100 ]
b1000000 \
1(
#20000
0(
#25000
b100 ]
b1000000 \
1(
#30000
0(
#35000
b100 ]
b1000000 \
1(
#40000
0(
#45000
0-
1(
#50000
0(
#55000
1(
#60000
0(
#65000
b0 e
1(
#70000
0(
#75000
b1 Y
0T
1S
b0 5
b0 V
b0 _
b0 9
b0 U
b0 ^
b0 X
b0 Z
b1 0
1*
1(
#80000
0(
#85000
b10 Y
0*
1(
#90000
0(
#95000
b11 Y
1[
17
b11 W
b100 \
b0 R
0P
1(
#100000
0(
#105000
16
b0 8
b0 A
b0 c
17
1(
#110000
0(
#115000
b100 Y
0[
17
16
1(
#120000
0(
#125000
16
b110 Y
b0 "
b0 :
b0 Q
07
b100 \
1(
#130000
0(
#135000
b0 Y
1!
06
1(
#140000
0(
#145000
0!
b100 e
1(
#150000
0(
#155000
b1 Y
b100 9
b100 U
b100 ^
b1 X
b10 0
1*
b100 )
b100 2
b100 ?
1(
#160000
0(
#165000
b10 Y
0*
1(
#170000
0(
#175000
b11 Y
1[
17
b11 W
b100 \
1(
#180000
0(
#185000
16
b101000 8
b101000 A
b101000 c
17
1(
#190000
0(
#195000
b100 Y
0[
17
16
1(
#200000
0(
#205000
16
b110 Y
b101000 "
b101000 :
b101000 Q
07
b100 \
1(
#210000
0(
#215000
b0 Y
1!
06
1(
#220000
0(
#225000
0!
b1000 e
1(
#230000
0(
#235000
b1 Y
b1000 9
b1000 U
b1000 ^
b10 X
b11 0
1*
b1000 )
b1000 2
b1000 ?
1(
#240000
0(
#245000
b10 Y
0*
1(
#250000
0(
#255000
b11 Y
1[
17
b11 W
b100 \
1(
#260000
0(
#265000
16
b1010000 8
b1010000 A
b1010000 c
17
1(
#270000
0(
#275000
b100 Y
0[
17
16
1(
#280000
0(
#285000
16
b110 Y
b1010000 "
b1010000 :
b1010000 Q
07
b100 \
1(
#290000
0(
#295000
b0 Y
1!
06
1(
#300000
0(
#305000
0!
b1100 e
1(
#310000
0(
#315000
b1 Y
b1100 9
b1100 U
b1100 ^
b11 X
b100 0
1*
b1100 )
b1100 2
b1100 ?
1(
#320000
0(
#325000
b10 Y
0*
1(
#330000
0(
#335000
b11 Y
1[
17
b11 W
b100 \
1(
#340000
0(
#345000
16
b1111000 8
b1111000 A
b1111000 c
17
1(
#350000
0(
#355000
b100 Y
0[
17
16
1(
#360000
0(
#365000
16
b110 Y
b1111000 "
b1111000 :
b1111000 Q
07
b100 \
1(
#370000
0(
#375000
b0 Y
1!
06
1(
#380000
0(
#385000
0!
b0 e
1(
#390000
0(
#395000
b1 Y
b0 9
b0 U
b0 ^
b0 X
b101 0
1*
b0 )
b0 2
b0 ?
1(
#400000
0(
#405000
b10 Y
0*
1(
#410000
0(
#415000
b110 Y
b0 "
b0 :
b0 Q
b10 W
b11 R
1P
b100 \
1(
#420000
0(
#425000
b0 Y
1!
1(
#430000
0(
#435000
0!
b100 e
1(
#440000
0(
#445000
b1 Y
b100 9
b100 U
b100 ^
b1 X
b110 0
1*
b100 )
b100 2
b100 ?
1(
#450000
0(
#455000
b10 Y
0*
1(
#460000
0(
#465000
b110 Y
b101000 "
b101000 :
b101000 Q
b10 W
b100 \
b11 R
1P
1(
#470000
0(
#475000
b0 Y
1!
1(
#480000
0(
#485000
0!
b1000 e
1(
#490000
0(
#495000
b1 Y
b1000 9
b1000 U
b1000 ^
b10 X
b111 0
1*
b1000 )
b1000 2
b1000 ?
1(
#500000
0(
#505000
b10 Y
0*
1(
#510000
0(
#515000
b110 Y
b1010000 "
b1010000 :
b1010000 Q
b10 W
b100 \
b11 R
1P
1(
#520000
0(
#525000
b0 Y
1!
1(
#530000
0(
#535000
0!
b11011110101011011011111011101111 g
b100000000 f
1(
#540000
0(
#545000
b1 Y
1T
0S
b11011110101011011011111011101111 5
b11011110101011011011111011101111 V
b11011110101011011011111011101111 _
b100000000 9
b100000000 U
b100000000 ^
b0 X
b1 Z
b1 1
1,
b11011110101011011011111011101111 +
b11011110101011011011111011101111 3
b11011110101011011011111011101111 @
b100000000 )
b100000000 2
b100000000 ?
1(
#550000
0(
#555000
b10 Y
0,
1(
#560000
0(
#565000
b101 Y
1[
14
b10 W
b100 \
b0 R
0P
1(
#570000
0(
#575000
14
16
1(
#580000
0(
#585000
16
b110 Y
0[
14
1(
#590000
0(
#595000
b0 Y
1!
04
16
1(
#600000
0(
#605000
06
0!
b11001010111111101011101010111110 g
b100000100 f
1(
#610000
0(
#615000
b1 Y
b11001010111111101011101010111110 5
b11001010111111101011101010111110 V
b11001010111111101011101010111110 _
b100000100 9
b100000100 U
b100000100 ^
b1 X
b10 1
1,
b11001010111111101011101010111110 +
b11001010111111101011101010111110 3
b11001010111111101011101010111110 @
b100000100 )
b100000100 2
b100000100 ?
1(
#620000
0(
#625000
b10 Y
0,
1(
#630000
0(
#635000
b101 Y
1[
14
b10 W
b100 \
1(
#640000
0(
#645000
16
14
1(
#650000
0(
#655000
b110 Y
0[
14
16
1(
#660000
0(
#665000
16
b0 Y
1!
04
1(
#670000
0(
#675000
0!
06
b10010001101000101011001111000 g
b100001000 f
1(
#680000
0(
#685000
b1 Y
b10010001101000101011001111000 5
b10010001101000101011001111000 V
b10010001101000101011001111000 _
b100001000 9
b100001000 U
b100001000 ^
b10 X
b11 1
1,
b10010001101000101011001111000 +
b10010001101000101011001111000 3
b10010001101000101011001111000 @
b100001000 )
b100001000 2
b100001000 ?
1(
#690000
0(
#695000
b10 Y
0,
1(
#700000
0(
#705000
b101 Y
1[
14
b10 W
b100 \
1(
#710000
0(
#715000
14
16
1(
#720000
0(
#725000
16
b110 Y
0[
14
1(
#730000
0(
#735000
b0 Y
1!
04
16
1(
#740000
0(
#745000
06
0!
b100000000 e
1(
#750000
0(
#755000
b1 Y
0T
1S
b100000000 9
b100000000 U
b100000000 ^
b0 X
b1000 0
1*
b100000000 )
b100000000 2
b100000000 ?
1(
#760000
0(
#765000
b10 Y
0*
1(
#770000
0(
#775000
b11 Y
1[
17
b10 W
b100 \
1(
#780000
0(
#785000
16
b11011110101011011011111011101111 8
b11011110101011011011111011101111 A
b11011110101011011011111011101111 c
17
1(
#790000
0(
#795000
b100 Y
0[
17
16
1(
#800000
0(
#805000
16
b110 Y
b11011110101011011011111011101111 "
b11011110101011011011111011101111 :
b11011110101011011011111011101111 Q
07
b100 \
1(
#810000
0(
#815000
b0 Y
1!
06
1(
#820000
0(
#825000
0!
b100000100 e
1(
#830000
0(
#835000
b1 Y
b100000100 9
b100000100 U
b100000100 ^
b1 X
b1001 0
1*
b100000100 )
b100000100 2
b100000100 ?
1(
#840000
0(
#845000
b10 Y
0*
1(
#850000
0(
#855000
b11 Y
1[
17
b10 W
b100 \
1(
#860000
0(
#865000
16
b11001010111111101011101010111110 8
b11001010111111101011101010111110 A
b11001010111111101011101010111110 c
17
1(
#870000
0(
#875000
b100 Y
0[
17
16
1(
#880000
0(
#885000
16
b110 Y
b11001010111111101011101010111110 "
b11001010111111101011101010111110 :
b11001010111111101011101010111110 Q
07
b100 \
1(
#890000
0(
#895000
b0 Y
1!
06
1(
#900000
0(
#905000
0!
b100001000 e
1(
#910000
0(
#915000
b1 Y
b100001000 9
b100001000 U
b100001000 ^
b10 X
b1010 0
1*
b100001000 )
b100001000 2
b100001000 ?
1(
#920000
0(
#925000
b10 Y
0*
1(
#930000
0(
#935000
b11 Y
1[
17
b10 W
b100 \
1(
#940000
0(
#945000
16
b10010001101000101011001111000 8
b10010001101000101011001111000 A
b10010001101000101011001111000 c
17
1(
#950000
0(
#955000
b100 Y
0[
17
16
1(
#960000
0(
#965000
16
b110 Y
b10010001101000101011001111000 "
b10010001101000101011001111000 :
b10010001101000101011001111000 Q
07
b100 \
1(
#970000
0(
#975000
b0 Y
1!
06
1(
#980000
0(
#985000
0!
b10000 e
1(
#990000
0(
#995000
b1 Y
b10000 9
b10000 U
b10000 ^
b100 X
b0 Z
b1011 0
1*
b10000 )
b10000 2
b10000 ?
1(
#1000000
0(
#1005000
b10 Y
0*
1(
#1010000
0(
#1015000
b11 Y
1[
17
b11 W
b100 \
1(
#1020000
0(
#1025000
16
b10100000 8
b10100000 A
b10100000 c
17
1(
#1030000
0(
#1035000
b100 Y
0[
17
16
1(
#1040000
0(
#1045000
16
b110 Y
b10100000 "
b10100000 :
b10100000 Q
07
b100 \
1(
#1050000
0(
#1055000
b0 Y
1!
06
1(
#1060000
0(
#1065000
0!
b10000010000 e
1(
#1070000
0(
#1075000
b1 Y
b10000010000 9
b10000010000 U
b10000010000 ^
b100 Z
b1100 0
1*
b10000010000 )
b10000010000 2
b10000010000 ?
1(
#1080000
0(
#1085000
b10 Y
0*
1(
#1090000
0(
#1095000
b11 Y
1[
17
b10 W
b100 \
1(
#1100000
0(
#1105000
16
b10100010100000 8
b10100010100000 A
b10100010100000 c
17
1(
#1110000
0(
#1115000
b100 Y
0[
17
16
1(
#1120000
0(
#1125000
16
b110 Y
b10100010100000 "
b10100010100000 :
b10100010100000 Q
07
b100 \
1(
#1130000
0(
#1135000
b0 Y
1!
06
1(
#1140000
0(
#1145000
0!
b100000010000 e
1(
#1150000
0(
#1155000
b1 Y
b100000010000 9
b100000010000 U
b100000010000 ^
b1000 Z
b1101 0
1*
b100000010000 )
b100000010000 2
b100000010000 ?
1(
#1160000
0(
#1165000
b10 Y
0*
1(
#1170000
0(
#1175000
b11 Y
1[
17
b1 W
b100 \
1(
#1180000
0(
#1185000
16
b101000010100000 8
b101000010100000 A
b101000010100000 c
17
1(
#1190000
0(
